pickax/__init__.py
pickax/areautil.py
pickax/blit_manager.py
pickax/distaz.py
pickax/dumppicks.py
pickax/eqtransform.py
pickax/exportdistaz.py
pickax/exportreal.py
pickax/exportvelest.py
pickax/flag.py
pickax/help.py
pickax/hypoinverse.py
pickax/mergepicks.py
pickax/pick_util.py
pickax/pickax.py
pickax/pickax_config.py
pickax/pickax_main.py
pickax/quake_iterator.py
pickax/seismogram_iterator.py
pickax/seismograph.py
pickax/station_iterator.py
pickax/traveltime.py
pickax/usgspicks.py
pickax/version.py
seismic_pickax-0.6.0.dist-info/LICENSE
seismic_pickax-0.6.0.dist-info/METADATA
seismic_pickax-0.6.0.dist-info/WHEEL
seismic_pickax-0.6.0.dist-info/entry_points.txt
seismic_pickax-0.6.0.dist-info/top_level.txt
seismic_pickax-0.6.0.dist-info/RECORD
