Metadata-Version: 2.1
Name: seismic-pickax
Version: 0.6.0
Summary: Seismic phase picker.
Author-email: Philip Crotwell <crotwell@seis.sc.edu>
Project-URL: Homepage, https://github.com/crotwell/pickax
Project-URL: Bug Tracker, https://github.com/crotwell/pickax/issues
Classifier: Programming Language :: Python :: 3
Classifier: License :: OSI Approved :: GNU Lesser General Public License v2 or later (LGPLv2+)
Classifier: Operating System :: OS Independent
Classifier: Intended Audience :: Science/Research
Classifier: Topic :: Scientific/Engineering
Requires-Python: >=3.10
License-File: LICENSE
Requires-Dist: obspy (>=1.4)
Requires-Dist: ipython (>=8)
